MANIFEST.in
README.md
pyproject.toml
setup.py
amuse_smalln.egg-info/PKG-INFO
amuse_smalln.egg-info/SOURCES.txt
amuse_smalln.egg-info/dependency_links.txt
amuse_smalln.egg-info/requires.txt
amuse_smalln.egg-info/top_level.txt
src/amuse/community/smalln/Makefile
src/amuse/community/smalln/__init__.py
src/amuse/community/smalln/_version.py
src/amuse/community/smalln/interface.cc
src/amuse/community/smalln/interface.py
src/amuse/community/smalln/scatter3.py
src/amuse/community/smalln/scatter32.py
src/amuse/community/smalln/test_smallN.py
src/amuse/community/smalln/src/Makefile
src/amuse/community/smalln/src/analyze.cc
src/amuse/community/smalln/src/f2c.c
src/amuse/community/smalln/src/f2c.h
src/amuse/community/smalln/src/hdyn.cc
src/amuse/community/smalln/src/hdyn.h
src/amuse/community/smalln/src/kepler.cc
src/amuse/community/smalln/src/kepler.h
src/amuse/community/smalln/src/nstab.c
src/amuse/community/smalln/src/nstab.h
src/amuse/community/smalln/src/smallN.cc
src/amuse/community/smalln/src/smallN_interface.cc
src/amuse/community/smalln/src/smallN_interface.h
src/amuse/community/smalln/src/smallN_unpert.cc
src/amuse/community/smalln/src/stdinc.h
src/amuse/community/smalln/src/util.cc
src/amuse/community/smalln/src/vec.h
support/__init__.py
support/classifiers.py
support/config.py
support/generate_main.py
support/getsp.class
support/getsp.java
support/misc.py
support/setup_codes.py
support/version.py